{
  "amishComboCount": 5,
  "astronautComboCount": 4,
  "ninjaComboCount": 6,
  "clownComboCount": 4,
  "chemicalComboCount": 4,
  "samuraiComboCount": 5,
  "rainbowComboCount": 3,
  "marineComboCount": 6,
  "zombieRagsComboCount": 2,
  "hockeyComboCount": 5,
  "sushiChefComboCount": 5,
  "taekwondoComboCount": 2,
  "tennisComboCount": 5,
  "basketballComboCount": 4,
  "oldFootballStarComboCount": 5,
  "youngFootballStarComboCount": 5,
  "stripedSoccerComboCount": 3,
  "spartanComboCount": 6,
  "knightComboCount": 6,
  "goldenSuitComboCount": 5,
  "tuxedoComboCount": 6,
  "plaidSuitComboCount": 5,
  "blackSuitComboCount": 6,
  "brownSuitComboCount": 5,
  "greySuitComboCount": 5,
  "golfComboCount": 5,
  "soccerArgentinaComboCount": 3,
  "soccerBrazilComboCount": 3,
  "nakedComboCount": 7,
  "stonerComboCount": 3,
  "partyDegenComboCount": 7  
}
